lingtypology/__init__.py
lingtypology/autotyp_lang_mapping.json
lingtypology/datasets.py
lingtypology/db_apis.py
lingtypology/glottolog-languoids-v4.0-26-gb2138530b3.csv
lingtypology/glottolog-languoids-v4.0-26-gb2138530b3.csv-metadata.json
lingtypology/glottolog.py
lingtypology/language_elevation_mapping.json
lingtypology/legend.html
lingtypology/lingtypology_exceptions.py
lingtypology/maps.py
lingtypology-0.8.6.dist-info/LICENSE.md
lingtypology-0.8.6.dist-info/METADATA
lingtypology-0.8.6.dist-info/WHEEL
lingtypology-0.8.6.dist-info/top_level.txt
lingtypology-0.8.6.dist-info/RECORD
