Metadata-Version: 2.1
Name: lingtypology
Version: 0.8.6
Summary: A tool for linguistic typology.
Home-page: https://github.com/OneAdder/lingtypology
Author: Michael Voronov
Author-email: mikivo@list.ru
License: GPLv3
Platform: UNKNOWN
Classifier: Programming Language :: Python :: 3
Classifier: Programming Language :: Python :: 3 :: Only
Classifier: License :: OSI Approved :: GNU General Public License v3 (GPLv3)
Classifier: Topic :: Scientific/Engineering
Classifier: Topic :: Scientific/Engineering :: Visualization
Classifier: Topic :: Text Processing :: Linguistic
Requires-Python: >=3.5
Requires-Dist: folium
Requires-Dist: branca
Requires-Dist: jinja2
Requires-Dist: pandas
Requires-Dist: pyglottolog
Requires-Dist: colour
Requires-Dist: matplotlib
Requires-Dist: selenium
Provides-Extra: test
Requires-Dist: pytest (>=3.6) ; extra == 'test'
Requires-Dist: pytest-cov ; extra == 'test'
Requires-Dist: coverage (>=4.2) ; extra == 'test'
